{
  "title": "Vintage Red Pyrex Refrigerator Glass Dish w/Lid (4.5x3.5x3.5)",
  "image_url": "https://cdn.shopify.com/s/files/1/0507/1506/6523/files/I332907195-17795574952905WL99PMM3HW4GGZIT9TP.jpg?v=1779557528",
  "estate_price": 10,
  "market_estimate": 32,
  "gross_profit": 22,
  "profit_pct": 225,
  "tier": "MEDIUM",
  "confidence": 90,
  "key_signals": "Pyrex refrigerator dishes in primary colors with original matching glass lids have high vintage kitchenware demand and consistent sell-through rates.",
  "estate_url": "https://mainstreetestatesales.com/products/vintage-red-pyrex-refrigerator-glass-dish-wlid-45x35x35-38080",
  "etsy_url": "",
  "google_url": "https://google.com/search?q=Vintage+Red+Pyrex+Refrigerator+Glass+Dish+w%2FLid",
  "scouted_at": "4:14 AM \u00b7 May 24, 2026",
  "alert_type": "roi"
}