{
  "title": "Vintage Cochrane Compressor Company Metal Advertising Thermometer - St. Louis, MO (~12.5\")",
  "image_url": "https://cdn.shopify.com/s/files/1/0507/1506/6523/files/I335263141-17806765975403E4ATVG414X5YRUDGXU3.jpg?v=1780676631",
  "estate_price": 16,
  "market_estimate": 60,
  "gross_profit": 44,
  "profit_pct": 275,
  "tier": "MEDIUM",
  "confidence": 85,
  "key_signals": "Vintage advertising thermometers with intact glass tubes and vibrant metal lithography are highly sought after by petroliana and industrial memorabilia collectors.",
  "estate_url": "https://mainstreetestatesales.com/products/vintage-cochrane-compressor-company-metal-advertising-thermometer-st-louis-mo-125-436df",
  "etsy_url": "",
  "google_url": "https://google.com/search?q=Vintage+Cochrane+Compressor+Company+Metal+Advertising+Thermometer+-+St.+Louis%2C+MO",
  "scouted_at": "4:09 AM \u00b7 June 6, 2026",
  "alert_type": "roi"
}